fasta2png/__init__.py
fasta2png/faa2png.py
fasta2png/fna2png.py
fasta2png-9.dist-info/licenses/LICENSE
fasta2png-9.dist-info/METADATA
fasta2png-9.dist-info/WHEEL
fasta2png-9.dist-info/entry_points.txt
fasta2png-9.dist-info/top_level.txt
fasta2png-9.dist-info/RECORD
