Metadata-Version: 2.4
Name: fasta2png
Version: 9
Summary: PNG visualization of nucleic acid or protein sequences
Author-email: Mete Balci <metebalci@gmail.com>
Project-URL: Homepage, https://github.com/metebalci/fasta2png
Project-URL: Documentation, https://github.com/metebalci/fasta2png
Project-URL: Repository, https://github.com/metebalci/fasta2png.git
Project-URL: Issues, https://github.com/metebalci/fasta2png/issues
Project-URL: Changelog, https://github.com/metebalci/fasta2png/blob/master/README.md
Keywords: fasta,fna,faa,png
Classifier: Development Status :: 3 - Alpha
Classifier: Environment :: Console
Classifier: License :: OSI Approved :: GNU General Public License v3 or later (GPLv3+)
Classifier: Programming Language :: Python :: 3
Classifier: Operating System :: OS Independent
Classifier: Topic :: Utilities
Requires-Python: >=3.12
License-File: LICENSE
Requires-Dist: Pillow>=11.1.0
Provides-Extra: dev
Requires-Dist: setuptools>=61.0; extra == "dev"
Requires-Dist: build; extra == "dev"
Requires-Dist: twine; extra == "dev"
Dynamic: license-file
